populse_db/__init__.py
populse_db/database.py
populse_db/filter.py
populse_db/server.py
populse_db/storage.py
populse_db/storage_api.py
populse_db/engine/__init__.py
populse_db/engine/sqlite.py
populse_db/test/__init__.py
populse_db/test/__main__.py
populse_db/test/test_base.py
populse_db/test/test_schema.py
populse_db/test/test_storage.py
populse_db/test/schema/__init__.py
populse_db/test/schema/dataset.py
populse_db/test/schema/processing.py
populse_db/test/schema/snapshot.py
populse_db/tutorial/__init__.py
populse_db/tutorial/tutorial_01.py
populse_db-3.0.19.dist-info/licenses/LICENSE
populse_db-3.0.19.dist-info/METADATA
populse_db-3.0.19.dist-info/WHEEL
populse_db-3.0.19.dist-info/top_level.txt
populse_db-3.0.19.dist-info/RECORD
