Metadata-Version: 2.4
Name: populse-db
Version: 3.0.19
Summary: populse-db
Author-email: Popolse Team <contact@brainvisa.info>
License: CeCILL-B
Project-URL: homepage, https://populse.github.io/populse_db/
Project-URL: repository, https://github.com/populse/populse_db
Classifier: Intended Audience :: Developers
Classifier: License :: OSI Approved
Classifier: Development Status :: 5 - Production/Stable
Classifier: Environment :: Console
Classifier: Operating System :: OS Independent
Classifier: Programming Language :: Python
Classifier: Programming Language :: Python :: 3.11
Classifier: Programming Language :: Python :: 3.12
Classifier: Programming Language :: Python :: 3.13
Classifier: Programming Language :: SQL
Classifier: Natural Language :: English
Classifier: Topic :: Database
Requires-Python: >=3.10
License-File: LICENSE
Requires-Dist: python-dateutil
Requires-Dist: lark>=0.7.0
Requires-Dist: cryptography
Requires-Dist: requests
Provides-Extra: doc
Requires-Dist: sphinx>=1.0; extra == "doc"
Provides-Extra: server
Requires-Dist: fastapi; extra == "server"
Requires-Dist: uvicorn; extra == "server"
Requires-Dist: tblib; extra == "server"
Dynamic: license-file
